odoo/addons/account_banking_mandate/README.rst
odoo/addons/account_banking_mandate/__init__.py
odoo/addons/account_banking_mandate/__manifest__.py
odoo/addons/account_banking_mandate/data/mandate_reference_sequence.xml
odoo/addons/account_banking_mandate/i18n/account_banking_mandate.pot
odoo/addons/account_banking_mandate/i18n/am.po
odoo/addons/account_banking_mandate/i18n/ar.po
odoo/addons/account_banking_mandate/i18n/ca.po
odoo/addons/account_banking_mandate/i18n/cs.po
odoo/addons/account_banking_mandate/i18n/da_DK.po
odoo/addons/account_banking_mandate/i18n/de.po
odoo/addons/account_banking_mandate/i18n/el_GR.po
odoo/addons/account_banking_mandate/i18n/es.po
odoo/addons/account_banking_mandate/i18n/es_AR.po
odoo/addons/account_banking_mandate/i18n/es_CR.po
odoo/addons/account_banking_mandate/i18n/es_EC.po
odoo/addons/account_banking_mandate/i18n/es_ES.po
odoo/addons/account_banking_mandate/i18n/es_MX.po
odoo/addons/account_banking_mandate/i18n/es_VE.po
odoo/addons/account_banking_mandate/i18n/et.po
odoo/addons/account_banking_mandate/i18n/fi.po
odoo/addons/account_banking_mandate/i18n/fr.po
odoo/addons/account_banking_mandate/i18n/fr_FR.po
odoo/addons/account_banking_mandate/i18n/gl.po
odoo/addons/account_banking_mandate/i18n/hr.po
odoo/addons/account_banking_mandate/i18n/it.po
odoo/addons/account_banking_mandate/i18n/lt.po
odoo/addons/account_banking_mandate/i18n/nb_NO.po
odoo/addons/account_banking_mandate/i18n/nl.po
odoo/addons/account_banking_mandate/i18n/nl_BE.po
odoo/addons/account_banking_mandate/i18n/pl.po
odoo/addons/account_banking_mandate/i18n/pt.po
odoo/addons/account_banking_mandate/i18n/pt_BR.po
odoo/addons/account_banking_mandate/i18n/pt_PT.po
odoo/addons/account_banking_mandate/i18n/ro.po
odoo/addons/account_banking_mandate/i18n/ru.po
odoo/addons/account_banking_mandate/i18n/sl.po
odoo/addons/account_banking_mandate/i18n/th.po
odoo/addons/account_banking_mandate/i18n/tr.po
odoo/addons/account_banking_mandate/i18n/vi.po
odoo14_addon_account_banking_mandate-14.0.2.1.0.dist-info/METADATA
odoo14_addon_account_banking_mandate-14.0.2.1.0.dist-info/WHEEL
odoo14_addon_account_banking_mandate-14.0.2.1.0.dist-info/top_level.txt
odoo14_addon_account_banking_mandate-14.0.2.1.0.dist-info/RECORD
